README.txt
ez_setup.py
setup.cfg
setup.py
bicop/__init__.py
bicop/config.py
bicop/nestdict.py
bicop/utils.py
bicop.egg-info/PKG-INFO
bicop.egg-info/SOURCES.txt
bicop.egg-info/dependency_links.txt
bicop.egg-info/top_level.txt
bicop.egg-info/zip-safe
bicop/tests/__init__.py
bicop/tests/testNestedDict.py
bicop/tests/testParse.py
bicop/tests/testUtils.py