Metadata-Version: 1.0
Name: bicop
Version: 1.0rc2
Summary: Read bind-style configuration files
Home-page: UNKNOWN
Author: Wichert Akkerman - Simplon
Author-email: wichert@wiggy.net
License: BSD
Keywords: configparser configuration parser ISC bind
Platform: UNKNOWN
Classifier: Development Status :: 6 - Mature
Classifier: Intended Audience :: Developers
Classifier: License :: OSI Approved :: BSD License
Classifier: Operating System :: OS Independent
Classifier: Programming Language :: Python
Classifier: Topic :: Software Development :: Libraries :: Python Modules
